fastcs_secop/__init__.py
fastcs_secop/_controllers.py
fastcs_secop/_io.py
fastcs_secop/_util.py
fastcs_secop/version.py
fastcs_secop-0.1.0.dist-info/licenses/LICENSE
fastcs_secop-0.1.0.dist-info/METADATA
fastcs_secop-0.1.0.dist-info/WHEEL
fastcs_secop-0.1.0.dist-info/top_level.txt
fastcs_secop-0.1.0.dist-info/RECORD
